[
    {
        "name": "player_m_l1",
        "health": 10,
        "maxHealth": 10,
        "attackSoundId": "m_physical_attack",
        "defendSoundId": "m_physical_defend",
        "hitSoundId": "m_physical_hit",
        "gender": "m",
        "gold": 100,
        "attributes": {
            "Strength": 1,
            "Constitution": 1,
            "Magic": 1,
            "Dexterity": 1,
            "Luck": 1,
            "Defense": 1
        },
        "posX": 35,
        "posY": -150,
        "width": 512,
        "height": 700,
        "scaleX": 0.65,
        "scaleY": 0.65
    }
]